babitmf-0.2.0.dist-info/licenses/LICENSE
bmf/BUILTIN_CONFIG.json
bmf/__init__.py
bmf/bin/bmf
bmf/bin/hmp_perf_main
bmf/bin/module_manager
bmf/bin/run_bmf_graph
bmf/bin/test_hmp
bmf/bin/trace_format_log
bmf/builder/__init__.py
bmf/builder/bmf.py
bmf/builder/bmf_graph.py
bmf/builder/bmf_modules.py
bmf/builder/bmf_node.py
bmf/builder/bmf_optimizer.py
bmf/builder/bmf_stream.py
bmf/builder/bmf_sync.py
bmf/builder/ff_filter.py
bmf/builder/graph_config.py
bmf/cmd/python_wrapper/wrapper.py
bmf/cpp_modules/Module_GoMockDecoder/libGoMockDecoder.dylib
bmf/cpp_modules/Module_GoMockDecoder/meta.info
bmf/cpp_modules/Module_MockDecoder/libMockDecoder.dylib
bmf/cpp_modules/Module_MockDecoder/meta.info
bmf/cpp_modules/Module_clock/libclock.dylib
bmf/cpp_modules/Module_clock/meta.info
bmf/cpp_modules/Module_pass_through/libpass_through.dylib
bmf/cpp_modules/Module_pass_through/meta.info
bmf/ffmpeg_engine/__init__.py
bmf/ffmpeg_engine/engine.py
bmf/hmp/__init__.py
bmf/hmp/tracer.py
bmf/include/builder.hpp
bmf/include/builder.ipp
bmf/include/c_android_vm.h
bmf/include/connector.hpp
bmf/include/connector_capi.h
bmf/include/connector_common.h
bmf/include/hmp_capi.h
bmf/include/running_info.h
bmf/include/bmf/sdk/.gitignore
bmf/include/bmf/sdk/audio_frame.h
bmf/include/bmf/sdk/av_convertor.h
bmf/include/bmf/sdk/bmf.h
bmf/include/bmf/sdk/bmf_av_packet.h
bmf/include/bmf/sdk/bmf_capi.h
bmf/include/bmf/sdk/bmf_kafka_reporter_interface.h
bmf/include/bmf/sdk/bmf_stat.h
bmf/include/bmf/sdk/bmf_type_info.h
bmf/include/bmf/sdk/cbytes.h
bmf/include/bmf/sdk/com_bytedance_bmf_API.h
bmf/include/bmf/sdk/common.h
bmf/include/bmf/sdk/config.h
bmf/include/bmf/sdk/config.h.in
bmf/include/bmf/sdk/convert_backend.h
bmf/include/bmf/sdk/error_define.h
bmf/include/bmf/sdk/exception_factory.h
bmf/include/bmf/sdk/ffmpeg_helper.h
bmf/include/bmf/sdk/filter_graph.h
bmf/include/bmf/sdk/hmp_import.h
bmf/include/bmf/sdk/json_param.h
bmf/include/bmf/sdk/log.h
bmf/include/bmf/sdk/log_buffer.h
bmf/include/bmf/sdk/media_description.h
bmf/include/bmf/sdk/module.h
babitmf-0.2.0.dist-info/METADATA
babitmf-0.2.0.dist-info/WHEEL
babitmf-0.2.0.dist-info/entry_points.txt
babitmf-0.2.0.dist-info/top_level.txt
babitmf-0.2.0.dist-info/RECORD
