Metadata-Version: 2.1
Name: BabitMF
Version: 0.2.0
Summary: Babit Multimedia Framework
Home-page: https://github.com/BabitMF/bmf
Author: 
Author-email: 
License: UNKNOWN
Platform: UNKNOWN
Requires-Python: >= 3.6
License-File: LICENSE
Requires-Dist: numpy (>=1.19.5)
Provides-Extra: templates
Requires-Dist: jinja2 ; extra == 'templates'
Requires-Dist: click ; extra == 'templates'
Requires-Dist: InquirerPy ; extra == 'templates'
Provides-Extra: test
Requires-Dist: pytest ; extra == 'test'
